pullrequest/__init__.py
pullrequest/bitbucket_cloud.py
pullrequest/cli.py
pullrequest/github.py
pullrequest/gitlab.py
pullrequest-0.1.4.dist-info/LICENSE.txt
pullrequest-0.1.4.dist-info/METADATA
pullrequest-0.1.4.dist-info/WHEEL
pullrequest-0.1.4.dist-info/entry_points.txt
pullrequest-0.1.4.dist-info/top_level.txt
pullrequest-0.1.4.dist-info/RECORD
