Metadata-Version: 2.1
Name: pullrequest
Version: 0.1.4
Summary: Create pullrequest to git service
Home-page: https://github.com/eerorika/pullrequest
Author: Eero Rikalainen
Author-email: eerorika@gmail.com
License: MIT
Platform: UNKNOWN
Requires-Dist: PyGithub
Requires-Dist: python-gitlab
Requires-Dist: requests-oauthlib
